rotating_proxies/__init__.py
rotating_proxies/expire.py
rotating_proxies/middlewares.py
rotating_proxies/policy.py
rotating_proxies/utils.py
scrapy_rotating_proxies_ng-0.7.0.dist-info/licenses/LICENSE.txt
scrapy_rotating_proxies_ng-0.7.0.dist-info/METADATA
scrapy_rotating_proxies_ng-0.7.0.dist-info/WHEEL
scrapy_rotating_proxies_ng-0.7.0.dist-info/top_level.txt
scrapy_rotating_proxies_ng-0.7.0.dist-info/RECORD
