Metadata-Version: 2.4
Name: scrapy-rotating-proxies-ng
Version: 0.7.0
Summary: Rotating proxies for Scrapy
Author-email: Mikhail Korobov <kmike84@gmail.com>
Maintainer-email: Michel Ace <divtiply@gmail.com>
License-Expression: MIT
Project-URL: source, https://github.com/divtiply/scrapy-rotating-proxies-ng
Classifier: Development Status :: 3 - Alpha
Classifier: Intended Audience :: Developers
Classifier: Framework :: Scrapy
Classifier: Operating System :: OS Independent
Classifier: Programming Language :: Python
Classifier: Programming Language :: Python :: 3
Classifier: Programming Language :: Python :: 3.9
Classifier: Programming Language :: Python :: 3.10
Classifier: Programming Language :: Python :: 3.11
Classifier: Programming Language :: Python :: 3.12
Classifier: Programming Language :: Python :: 3.13
Requires-Python: >=3.9
License-File: LICENSE.txt
Requires-Dist: scrapy>=2.10
Requires-Dist: typing-extensions>=4.10.0
Dynamic: license-file
